{
    "version": "1.0.0",
    "discord": {
        "clientId": "1470719440726528042",
        "smallImageText": "NeoForge Launcher",
        "smallImageKey": "seal-circle"
    },
    "rss": "https://example.com/news.rss",
    "servers": [
        {
            "id": "survival",
            "name": "메인 서버",
            "description": "메인 서버입니다. 야생으로 바로 연결됩니다.",
            "icon": "",
            "version": "1.0.0",
            "address": "100.69.100.39:25565",
            "minecraftVersion": "1.21.1",
            "mainServer": true,
            "autoconnect": true,
            "javaOptions": {
                "supported": ">=17",
                "suggestedMajor": 17,
                "ram": {
                    "recommended": 4096,
                    "minimum": 2048
                }
            },
            "modules": [
                {
                    "id": "net.neoforged:neoforge:21.1.228",
                    "name": "NeoForge",
                    "type": "ForgeHosted",
                    "required": {
                        "value": true,
                        "def": true
                    },
                    "artifact": {
                        "size": 6961386,
                        "hash": "",
                        "url": "https://r2.sunharu.dev/neoforge-21.1.228-installer.jar"
                    },
                    "subModules": [
                        {
                            "id": "net.neoforged:neoforge:21.1.228-manifest",
                            "name": "NeoForge Manifest",
                            "type": "VersionManifest",
                            "required": {
                                "value": true,
                                "def": true
                            },
                            "artifact": {
                                "size": 21148,
                                "url": "https://r2.sunharu.dev/21.1.228-manifast.json"
                            }
                        }
                    ]
                },
                {
                    "id": "create:mod:1.21.1@jar",
                    "name": "기본 Create 모드",
                    "type": "ForgeMod",
                    "required": {
                        "value": true,
                        "def": false
                    },
                    "artifact": {
                        "size": 19123767,
                        "url": "https://r2.sunharu.dev/create-1.21.1-6.0.10.jar"
                    }
                },
                {
                    "id": "create_aero:mod:1.21.1@jar",
                    "name": "Create 항공학 모드",
                    "type": "ForgeMod",
                    "required": {
                        "value": true,
                        "def": false
                    },
                    "artifact": {
                        "size": 33003314,
                        "url": "https://r2.sunharu.dev/create-aeronautics-bundled-1.21.1-1.1.3.jar"
                    }
                },
                {
                    "id": "create_farming:mod:1.21.1@jar",
                    "name": "Create 파밍 모드",
                    "type": "ForgeMod",
                    "required": {
                        "value": true,
                        "def":false
                    },
                    "artifact": {
                        "size": 408059,
                        "url": "https://r2.sunharu.dev/create-integrated-farming-1.2.2.jar"
                    },
                    "subModules": [
                        {
                            "id": "create_farming:submod:1.21.1@jar",
                            "name": "Create 파밍 모드의 부가 모드",
                            "type": "ForgeMod",
                            "required": {
                                "value": true,
                                "def": true
                            },
                            "artifact": {
                                "size": 756460,
                                "url": "https://r2.sunharu.dev/CreateDragonsPlus-1.10.0b.jar"
                            }
                        }
                    ]
                },
                {
                    "id": "create_goggle:mod:1.21.1@jar",
                    "name": "Create 고글 모드",
                    "type": "ForgeMod",
                    "required": {
                        "value": true,
                        "def":false
                    },
                    "artifact": {
                        "size": 180932,
                        "url": "https://r2.sunharu.dev/creategoggles-1.21.1-6.1.1-%5BNEOFORGE%5D.jar"
                    },
                    "subModules": [
                        {
                            "id": "create_goggle:submod:1.21.1@jar",
                            "name": "Create 고글 모드의 부가 모드",
                            "type": "ForgeMod",
                            "required": {
                                "value": true,
                                "def": true
                            },
                            "artifact": {
                                "size": 584004,
                                "url": "https://r2.sunharu.dev/architectury-13.0.8-neoforge.jar"
                            }
                        }
                    ]
                },
                {
                    "id": "create_shulkvault:mod:1.21.1@jar",
                    "name": "Create 셜커 금고 모드",
                    "type": "ForgeMod",
                    "required": {
                        "value": true,
                        "def":false
                    },
                    "artifact": {
                        "size": 91230,
                        "url": "https://r2.sunharu.dev/shulkervault-1.0.1.jar"
                    }
                },
                {
                    "id": "create_slice:mod:1.21.1@jar",
                    "name": "Create 음식 모드",
                    "type": "ForgeMod",
                    "required": {
                        "value": true,
                        "def":false
                    },
                    "artifact": {
                        "size": 406699,
                        "url": "https://r2.sunharu.dev/sliceanddice-forge-4.2.4.jar"
                    },
                    "subModules": [
                        {
                            "id": "create_slice:submod:1.21.1@jar",
                            "name": "Create 음식 모드의 부가 모드",
                            "type": "ForgeMod",
                            "required": {
                                "value": true,
                                "def": true
                            },
                            "artifact": {
                                "size": 6869790,
                                "url": "https://r2.sunharu.dev/kotlinforforge-5.11.0-all.jar"
                            }
                        }
                    ]
                },
                {
                    "id": "create:submod:1.21.1@jar",
                    "name": "Create의 여러 모드에 들어가는 부가 모드",
                    "type": "ForgeMod",
                    "required": {
                        "value": true,
                        "def": false
                    },
                    "artifact": {
                        "size": 12719293,
                        "url": "https://r2.sunharu.dev/sable-neoforge-1.21.1-1.2.2.jar"
                    }
                },
                {
                    "id": "koreanPatch:mod:1.21.1@jar",
                    "name": "한국어 패치 모드",
                    "type": "ForgeMod",
                    "required": {
                        "value": true,
                        "def": false
                    },
                    "artifact": {
                        "size": 310970,
                        "url": "https://r2.sunharu.dev/ReduceMods/koreanpatch-neoforge-1.9.5%2Bmc1.21.jar"
                    }
                },
                {
                    "id": "Reduce_ImmediatelyFast:mod:1.21.1@jar",
                    "name": "ImmediatelyFast 최적화 모드",
                    "type": "ForgeMod",
                    "required": {
                        "value": false,
                        "def":false
                    },
                    "artifact": {
                        "size": 368598,
                        "url": "https://r2.sunharu.dev/ReduceMods/ImmediatelyFast-NeoForge-1.6.10%2B1.21.1.jar"
                    }
                },
                {
                    "id": "Reduce_DynamicFPS:mod:1.21.1@jar",
                    "name": "DynamicFPS 최적화 모드",
                    "type": "ForgeMod",
                    "required": {
                        "value": false,
                        "def":false
                    },
                    "artifact": {
                        "size": 220193,
                        "url": "https://r2.sunharu.dev/ReduceMods/dynamic-fps-3.11.4%2Bminecraft-1.21.0-neoforge.jar"
                    }
                },
                {
                    "id": "Reduce_entityculling:mod:1.21.1@jar",
                    "name": "entityculling 최적화 모드",
                    "type": "ForgeMod",
                    "required": {
                        "value": false,
                        "def":false
                    },
                    "artifact": {
                        "size": 1578350,
                        "url": "https://r2.sunharu.dev/ReduceMods/entityculling-neoforge-1.10.1-mc1.21.1.jar"
                    }
                },
                {
                    "id": "Reduce_ferritecore:mod:1.21.1@jar",
                    "name": "ferritecore 최적화 모드",
                    "type": "ForgeMod",
                    "required": {
                        "value": false,
                        "def":false
                    },
                    "artifact": {
                        "size": 121559,
                        "url": "https://r2.sunharu.dev/ReduceMods/ferritecore-7.0.3-neoforge.jar"
                    }
                },
                {
                    "id": "Reduce_lithium:mod:1.21.1@jar",
                    "name": "lithium 최적화 모드",
                    "type": "ForgeMod",
                    "required": {
                        "value": false,
                        "def":false
                    },
                    "artifact": {
                        "size": 774148,
                        "url": "https://r2.sunharu.dev/ReduceMods/lithium-neoforge-0.15.3%2Bmc1.21.1.jar"
                    }
                },
                {
                    "id": "Reduce_modernfix:mod:1.21.1@jar",
                    "name": "modernfix 최적화 모드",
                    "type": "ForgeMod",
                    "required": {
                        "value": false,
                        "def":false
                    },
                    "artifact": {
                        "size": 562031,
                        "url": "https://r2.sunharu.dev/ReduceMods/modernfix-neoforge-5.27.3%2Bmc1.21.1.jar"
                    }
                },
                {
                    "id": "Reduce_moreculling:mod:1.21.1@jar",
                    "name": "entityculling 최적화 모드의 확장판",
                    "type": "ForgeMod",
                    "required": {
                        "value": false,
                        "def":false
                    },
                    "artifact": {
                        "size": 344279,
                        "url": "https://r2.sunharu.dev/ReduceMods/moreculling-neoforge-1.21.1-1.0.7.jar"
                    }
                },
                {
                    "id": "Reduce_sodiumExtra:mod:1.21.1@jar",
                    "name": "Sodium 최적화 모드의 확장판",
                    "type": "ForgeMod",
                    "required": {
                        "value": false,
                        "def":false
                    },
                    "artifact": {
                        "size": 367047,
                        "url": "https://r2.sunharu.dev/ReduceMods/sodium-extra-neoforge-0.6.0%2Bmc1.21.1.jar"
                    }
                },
                {
                    "id": "Reduce_sodium:mod:1.21.1@jar",
                    "name": "Sodium 최적화 모드",
                    "type": "ForgeMod",
                    "required": {
                        "value": false,
                        "def":false
                    },
                    "artifact": {
                        "size": 1162994,
                        "url": "https://r2.sunharu.dev/ReduceMods/sodium-neoforge-0.6.13%2Bmc1.21.1.jar"
                    }
                }
            ]
        }
    ]
}